{"nodes": [{"id": "sample_sirb_samoya", "label": "Seafarer's Identity and Record Book \u00e2\u20ac\u201d Samoya (SIRB PDF)", "file_type": "document", "source_file": "sample_data/SIRB_Samoya.pdf", "source_location": null, "source_url": null, "captured_at": null, "author": null, "contributor": null}], "edges": [{"source": "sample_sirb_samoya", "target": "assignment_document_taxonomy", "relation": "conceptually_related_to", "confidence": "INFERRED", "confidence_score": 0.9, "source_file": "sample_data/SIRB_Samoya.pdf", "source_location": null, "weight": 0.9}], "hyperedges": []}